reviews/__init__.py
reviews/__main__.py
reviews/commands.py
reviews/controller.py
reviews/errors.py
reviews/version.py
reviews/cli/__init__.py
reviews/cli/main.py
reviews/config/__init__.py
reviews/config/commands.py
reviews/config/controller.py
reviews/config/helpers.py
reviews/config/settings.py
reviews/layout/__init__.py
reviews/layout/helpers.py
reviews/source_control/__init__.py
reviews/source_control/client.py
reviews/source_control/models.py
tests/__init__.py
tests/conftest.py
tests/test_config.py
tests/source_control/__init__.py
tests/source_control/models/__init__.py
tests/source_control/models/test_pull_request.py
reviews-0.6.0.dist-info/LICENSE.md
reviews-0.6.0.dist-info/METADATA
reviews-0.6.0.dist-info/WHEEL
reviews-0.6.0.dist-info/entry_points.txt
reviews-0.6.0.dist-info/top_level.txt
reviews-0.6.0.dist-info/RECORD
