Metadata-Version: 2.1
Name: reviews
Version: 0.6.0
Summary: A terminal UI dashboard to monitor requests for code review across Github repositories.
Home-page: https://github.com/apoclyps/reviews
Download-URL: https://pypi.org/project/reviews/
Author: Kyle Harrison
Author-email: kyle.harrison.dev@gmail.com
License: MIT
Project-URL: Funding, https://ko-fi.com/apoclyps
Project-URL: Say Thanks!, https://twitter.com/apoclyps
Project-URL: Source, https://github.com/apoclyps/reviews
Project-URL: Tracker, https://github.com/apoclyps/reviews/issues
Keywords: Reviews,pull request review
Classifier: Development Status :: 3 - Alpha
Classifier: Environment :: Console
Classifier: Intended Audience :: Developers
Classifier: License :: OSI Approved :: MIT License
Classifier: Natural Language :: English
Classifier: Operating System :: MacOS
Classifier: Operating System :: Microsoft :: Windows :: Windows 10
Classifier: Operating System :: Unix
Classifier: Programming Language :: Python :: 3.9
Classifier: Topic :: Terminals
License-File: LICENSE.md
